document_intelligence_wrapper/__init__.py
document_intelligence_wrapper/document_intelligence_client.py
document_intelligence_wrapper/extractors/__init__.py
document_intelligence_wrapper/extractors/document_processor.py
document_intelligence_wrapper/extractors/extract_utils.py
document_intelligence_wrapper/extractors/pdf_text_extractor.py
document_intelligence_wrapper-1.0.0.dist-info/LICENSE
document_intelligence_wrapper-1.0.0.dist-info/METADATA
document_intelligence_wrapper-1.0.0.dist-info/WHEEL
document_intelligence_wrapper-1.0.0.dist-info/top_level.txt
document_intelligence_wrapper-1.0.0.dist-info/RECORD
