Metadata-Version: 2.1
Name: document-intelligence-wrapper
Version: 1.0.0
Summary: A wrapper around Azure Document Intelligence for processing PDFs and extracting text.
Home-page: https://github.com/Ankit2230/document_intelligence_wrapper
Author: Ankit Khandelwal
Author-email: ankitkhandelwal18@icloud.com
Classifier: Programming Language :: Python :: 3
Classifier: Programming Language :: Python :: 3.10
Classifier: Programming Language :: Python :: 3.11
Classifier: License :: OSI Approved :: MIT License
Classifier: Operating System :: OS Independent
Requires-Python: >=3.10
License-File: LICENSE
Requires-Dist: tabulate==0.9.0
Requires-Dist: azure-ai-documentintelligence==1.0.0b3
Requires-Dist: pandas==2.2.2
